nexamem/__init__.py
nexamem/aimemory.py
nexamem/audit.py
nexamem/channels.py
nexamem/config.py
nexamem/content_processor.py
nexamem/history.py
nexamem/memory_scope.py
nexamem/metrics.py
nexamem/new_aimemory.py
nexamem/policy.py
nexamem/py.typed
nexamem/redis_adapter.py
nexamem/config/__init__.py
nexamem/config/aimemory.py
nexamem/config/storage.py
nexamem/di/__init__.py
nexamem/di/container.py
nexamem/di/providers.py
nexamem/storage/__init__.py
nexamem/storage/azure_redis.py
nexamem/storage/base.py
nexamem/storage/factory.py
nexamem/storage/file.py
nexamem/storage/memory.py
nexamem/storage/sqlite.py
nexamem-0.4.2.dist-info/licenses/LICENSE
nexamem-0.4.2.dist-info/METADATA
nexamem-0.4.2.dist-info/WHEEL
nexamem-0.4.2.dist-info/top_level.txt
nexamem-0.4.2.dist-info/RECORD
