Metadata-Version: 2.4
Name: nexamem
Version: 0.4.2
Summary: NexaMem/AIMemory - Complete enterprise-grade Redis-backed conversational memory with built-in governance, Azure integration, content processing, and audit capabilities. Everything included - no extras needed!
Author-email: Chad Adams <chadada@microsoft.com>
Maintainer-email: Chad Adams <chadada@microsoft.com>
License:     MIT License
Project-URL: Homepage, https://github.com/microsoft/nexamem
Project-URL: Documentation, https://github.com/microsoft/nexamem/blob/main/README.md
Project-URL: Repository, https://github.com/microsoft/nexamem.git
Project-URL: Bug Tracker, https://github.com/microsoft/nexamem/issues
Project-URL: Changelog, https://github.com/microsoft/nexamem/releases
Project-URL: Discussions, https://github.com/microsoft/nexamem/discussions
Keywords: aimemory,nexamem,chatbot,conversation,memory,llm,ai,redis,azure,governance,policy,audit,compliance,pii,content-processing,enterprise,async,channels
Classifier: Development Status :: 4 - Beta
Classifier: Intended Audience :: Developers
Classifier: Intended Audience :: Information Technology
Classifier: Topic :: Software Development :: Libraries :: Python Modules
Classifier: Topic :: Scientific/Engineering :: Artificial Intelligence
Classifier: Topic :: Database :: Database Engines/Servers
Classifier: Topic :: System :: Logging
Classifier: Programming Language :: Python :: 3
Classifier: Programming Language :: Python :: 3.8
Classifier: Programming Language :: Python :: 3.9
Classifier: Programming Language :: Python :: 3.10
Classifier: Programming Language :: Python :: 3.11
Classifier: Programming Language :: Python :: 3.12
Classifier: Programming Language :: Python :: 3.13
Classifier: License :: OSI Approved :: MIT License
Classifier: Operating System :: OS Independent
Classifier: Environment :: Web Environment
Classifier: Framework :: AsyncIO
Classifier: Typing :: Typed
Requires-Python: >=3.8
License-File: LICENSE
Requires-Dist: pydantic<3.0,>=2.0
Requires-Dist: redis<6.0,>=5.0.0
Requires-Dist: fakeredis==2.21.0
Requires-Dist: PyYAML<7.0,>=6.0
Requires-Dist: azure-identity<2.0,>=1.15.0
Requires-Dist: azure-keyvault-secrets<5.0,>=4.7.0
Provides-Extra: dev
Requires-Dist: pytest<9.0,>=7.0.0; extra == "dev"
Requires-Dist: pytest-asyncio<2.0,>=0.21.0; extra == "dev"
Requires-Dist: pytest-cov<7.0,>=4.0.0; extra == "dev"
Requires-Dist: black<25.0,>=23.0.0; extra == "dev"
Requires-Dist: mypy<2.0,>=1.0.0; extra == "dev"
Requires-Dist: ruff<1.0,>=0.1.0; extra == "dev"
Requires-Dist: pre-commit<4.0,>=3.0.0; extra == "dev"
Provides-Extra: docs
Requires-Dist: mkdocs<2.0,>=1.5.0; extra == "docs"
Requires-Dist: mkdocs-material<10.0,>=9.0.0; extra == "docs"
Requires-Dist: mkdocstrings[python]<1.0,>=0.20.0; extra == "docs"
Provides-Extra: perf
Requires-Dist: pytest-benchmark<5.0,>=4.0.0; extra == "perf"
Requires-Dist: memory-profiler<1.0,>=0.60.0; extra == "perf"
Provides-Extra: all
Requires-Dist: nexamem[dev,docs,perf]; extra == "all"
Dynamic: license-file
